{"artist":{"name":"Commander Cody","mbid":"09351b98-ff1d-47d8-8f29-a7678eabb57b","url":"https://www.last.fm/music/Commander+Cody","image":[{"#text":"https://lastfm-img2.akamaized.net/i/u/34s/e806881d525041e092b2ba13648e7598.png","size":"small"},{"#text":"https://lastfm-img2.akamaized.net/i/u/64s/e806881d525041e092b2ba13648e7598.png","size":"medium"},{"#text":"https://lastfm-img2.akamaized.net/i/u/174s/e806881d525041e092b2ba13648e7598.png","size":"large"},{"#text":"https://lastfm-img2.akamaized.net/i/u/300x300/e806881d525041e092b2ba13648e7598.png","size":"extralarge"},{"#text":"https://lastfm-img2.akamaized.net/i/u/300x300/e806881d525041e092b2ba13648e7598.png","size":"mega"},{"#text":"https://lastfm-img2.akamaized.net/i/u/300x300/e806881d525041e092b2ba13648e7598.png","size":""}],"streamable":"0","ontour":"0","stats":{"listeners":"13139","playcount":"72067"},"similar":{"artist":[{"name":"Commander Cody And His Lost Planet Airmen","url":"https://www.last.fm/music/Commander+Cody+And+His+Lost+Planet+Airmen","image":[{"#text":"https://lastfm-img2.akamaized.net/i/u/34s/067c3222ed8647e281984de6def621bb.png","size":"small"},{"#text":"https://lastfm-img2.akamaized.net/i/u/64s/067c3222ed8647e281984de6def621bb.png","size":"medium"},{"#text":"https://lastfm-img2.akamaized.net/i/u/174s/067c3222ed8647e281984de6def621bb.png","size":"large"},{"#text":"https://lastfm-img2.akamaized.net/i/u/300x300/067c3222ed8647e281984de6def621bb.png","size":"extralarge"},{"#text":"https://lastfm-img2.akamaized.net/i/u/300x300/067c3222ed8647e281984de6def621bb.png","size":"mega"},{"#text":"https://lastfm-img2.akamaized.net/i/u/300x300/067c3222ed8647e281984de6def621bb.png","size":""}]},{"name":"Bill Kirchen","url":"https://www.last.fm/music/Bill+Kirchen","image":[{"#text":"https://lastfm-img2.akamaized.net/i/u/34s/599a811cee5d4457bc92a50dd029d953.png","size":"small"},{"#text":"https://lastfm-img2.akamaized.net/i/u/64s/599a811cee5d4457bc92a50dd029d953.png","size":"medium"},{"#text":"https://lastfm-img2.akamaized.net/i/u/174s/599a811cee5d4457bc92a50dd029d953.png","size":"large"},{"#text":"https://lastfm-img2.akamaized.net/i/u/300x300/599a811cee5d4457bc92a50dd029d953.png","size":"extralarge"},{"#text":"https://lastfm-img2.akamaized.net/i/u/300x300/599a811cee5d4457bc92a50dd029d953.png","size":"mega"},{"#text":"https://lastfm-img2.akamaized.net/i/u/300x300/599a811cee5d4457bc92a50dd029d953.png","size":""}]},{"name":"BR5-49","url":"https://www.last.fm/music/BR5-49","image":[{"#text":"https://lastfm-img2.akamaized.net/i/u/34s/12898be15b584dbb9cfe1a49b6afebbe.png","size":"small"},{"#text":"https://lastfm-img2.akamaized.net/i/u/64s/12898be15b584dbb9cfe1a49b6afebbe.png","size":"medium"},{"#text":"https://lastfm-img2.akamaized.net/i/u/174s/12898be15b584dbb9cfe1a49b6afebbe.png","size":"large"},{"#text":"https://lastfm-img2.akamaized.net/i/u/300x300/12898be15b584dbb9cfe1a49b6afebbe.png","size":"extralarge"},{"#text":"https://lastfm-img2.akamaized.net/i/u/300x300/12898be15b584dbb9cfe1a49b6afebbe.png","size":"mega"},{"#text":"https://lastfm-img2.akamaized.net/i/u/300x300/12898be15b584dbb9cfe1a49b6afebbe.png","size":""}]},{"name":"Willie Nelson & Asleep At The Wheel","url":"https://www.last.fm/music/Willie+Nelson+&+Asleep+At+The+Wheel","image":[{"#text":"https://lastfm-img2.akamaized.net/i/u/34s/e0dd44e51bc44814a6bdb1bc2dda3e5d.png","size":"small"},{"#text":"https://lastfm-img2.akamaized.net/i/u/64s/e0dd44e51bc44814a6bdb1bc2dda3e5d.png","size":"medium"},{"#text":"https://lastfm-img2.akamaized.net/i/u/174s/e0dd44e51bc44814a6bdb1bc2dda3e5d.png","size":"large"},{"#text":"https://lastfm-img2.akamaized.net/i/u/300x300/e0dd44e51bc44814a6bdb1bc2dda3e5d.png","size":"extralarge"},{"#text":"https://lastfm-img2.akamaized.net/i/u/300x300/e0dd44e51bc44814a6bdb1bc2dda3e5d.png","size":"mega"},{"#text":"https://lastfm-img2.akamaized.net/i/u/300x300/e0dd44e51bc44814a6bdb1bc2dda3e5d.png","size":""}]},{"name":"The Amazing Rhythm Aces","url":"https://www.last.fm/music/The+Amazing+Rhythm+Aces","image":[{"#text":"https://lastfm-img2.akamaized.net/i/u/34s/cab2834a38dd4155af67720e3af7395f.png","size":"small"},{"#text":"https://lastfm-img2.akamaized.net/i/u/64s/cab2834a38dd4155af67720e3af7395f.png","size":"medium"},{"#text":"https://lastfm-img2.akamaized.net/i/u/174s/cab2834a38dd4155af67720e3af7395f.png","size":"large"},{"#text":"https://lastfm-img2.akamaized.net/i/u/300x300/cab2834a38dd4155af67720e3af7395f.png","size":"extralarge"},{"#text":"https://lastfm-img2.akamaized.net/i/u/300x300/cab2834a38dd4155af67720e3af7395f.png","size":"mega"},{"#text":"https://lastfm-img2.akamaized.net/i/u/300x300/cab2834a38dd4155af67720e3af7395f.png","size":""}]}]},"tags":{"tag":[{"name":"country","url":"https://www.last.fm/tag/country"},{"name":"rock","url":"https://www.last.fm/tag/rock"},{"name":"oldies","url":"https://www.last.fm/tag/oldies"},{"name":"rock n roll","url":"https://www.last.fm/tag/rock+n+roll"},{"name":"western swing","url":"https://www.last.fm/tag/western+swing"}]},"bio":{"links":{"link":{"#text":"","rel":"original","href":"https://last.fm/music/Commander+Cody/+wiki"}},"published":"25 Feb 2007, 23:22","summary":"aka known as Commander Cody and His Lost Planet Airmen, Cody plays a boogie woogie influenced blend of americana comparable to UK pub rock scene faves like Dave Edmunds, Nick Lowe and Brinsley Schwarz.\n\nRead Full Bio Here: Commander Cody Bio\n\nOfficial Website: Commander Cody <a href=\"https://www.last.fm/music/Commander+Cody\">Read more on Last.fm</a>","content":"aka known as Commander Cody and His Lost Planet Airmen, Cody plays a boogie woogie influenced blend of americana comparable to UK pub rock scene faves like Dave Edmunds, Nick Lowe and Brinsley Schwarz.\n\nRead Full Bio Here: Commander Cody Bio\n\nOfficial Website: Commander Cody <a href=\"https://www.last.fm/music/Commander+Cody\">Read more on Last.fm</a>. User-contributed text is available under the Creative Commons By-SA License; additional terms may apply."}}}