{"artist":{"name":"Eko Fresh feat. Summer Cem","mbid":"3db42aef-5961-4c75-8f0f-432c9db2a894","url":"https://www.last.fm/music/Eko+Fresh+feat.+Summer+Cem","image":[{"#text":"","size":"small"},{"#text":"","size":"medium"},{"#text":"","size":"large"},{"#text":"","size":"extralarge"},{"#text":"","size":"mega"},{"#text":"","size":""}],"streamable":"0","ontour":"0","stats":{"listeners":"329","playcount":"1128"},"similar":{"artist":[{"name":"Eko Fresh feat. G-Style","url":"https://www.last.fm/music/Eko+Fresh+feat.+G-Style","image":[{"#text":"https://lastfm-img2.akamaized.net/i/u/34s/6b9347fec5f6434dc3de5037b0621cdf.png","size":"small"},{"#text":"https://lastfm-img2.akamaized.net/i/u/64s/6b9347fec5f6434dc3de5037b0621cdf.png","size":"medium"},{"#text":"https://lastfm-img2.akamaized.net/i/u/174s/6b9347fec5f6434dc3de5037b0621cdf.png","size":"large"},{"#text":"https://lastfm-img2.akamaized.net/i/u/300x300/6b9347fec5f6434dc3de5037b0621cdf.png","size":"extralarge"},{"#text":"https://lastfm-img2.akamaized.net/i/u/300x300/6b9347fec5f6434dc3de5037b0621cdf.png","size":"mega"},{"#text":"https://lastfm-img2.akamaized.net/i/u/300x300/6b9347fec5f6434dc3de5037b0621cdf.png","size":""}]},{"name":"Eko Fresh feat. Capkekz","url":"https://www.last.fm/music/Eko+Fresh+feat.+Capkekz","image":[{"#text":"","size":"small"},{"#text":"","size":"medium"},{"#text":"","size":"large"},{"#text":"","size":"extralarge"},{"#text":"","size":"mega"},{"#text":"","size":""}]},{"name":"Eko Fresh feat. Farid Bang","url":"https://www.last.fm/music/Eko+Fresh+feat.+Farid+Bang","image":[{"#text":"https://lastfm-img2.akamaized.net/i/u/34s/59f811a81c204d1487052a2cf3635135.png","size":"small"},{"#text":"https://lastfm-img2.akamaized.net/i/u/64s/59f811a81c204d1487052a2cf3635135.png","size":"medium"},{"#text":"https://lastfm-img2.akamaized.net/i/u/174s/59f811a81c204d1487052a2cf3635135.png","size":"large"},{"#text":"https://lastfm-img2.akamaized.net/i/u/300x300/59f811a81c204d1487052a2cf3635135.png","size":"extralarge"},{"#text":"https://lastfm-img2.akamaized.net/i/u/300x300/59f811a81c204d1487052a2cf3635135.png","size":"mega"},{"#text":"https://lastfm-img2.akamaized.net/i/u/300x300/59f811a81c204d1487052a2cf3635135.png","size":""}]},{"name":"Eko Fresh feat. Tha Outlawz","url":"https://www.last.fm/music/Eko+Fresh+feat.+Tha+Outlawz","image":[{"#text":"","size":"small"},{"#text":"","size":"medium"},{"#text":"","size":"large"},{"#text":"","size":"extralarge"},{"#text":"","size":"mega"},{"#text":"","size":""}]},{"name":"Eko Fresh feat. Gangsta Lu","url":"https://www.last.fm/music/Eko+Fresh+feat.+Gangsta+Lu","image":[{"#text":"","size":"small"},{"#text":"","size":"medium"},{"#text":"","size":"large"},{"#text":"","size":"extralarge"},{"#text":"","size":"mega"},{"#text":"","size":""}]}]},"tags":{"tag":[]},"bio":{"links":{"link":{"#text":"","rel":"original","href":"https://last.fm/music/Eko+Fresh+feat.+Summer+Cem/+wiki"}},"published":"01 Jan 1970, 00:00","summary":" <a href=\"https://www.last.fm/music/Eko+Fresh+feat.+Summer+Cem\">Read more on Last.fm</a>","content":""}}}